djangogoboot/__init__.py
djangogoboot/main.py
djangogoboot/repo.py
djangogoboot/settings.py
djangogoboot/ssh.py
djangogoboot/utils.py
djangogoboot-1.0.2.dist-info/entry_points.txt
djangogoboot-1.0.2.dist-info/LICENSE
djangogoboot-1.0.2.dist-info/WHEEL
djangogoboot-1.0.2.dist-info/METADATA
djangogoboot-1.0.2.dist-info/RECORD
