Metadata-Version: 2.1
Name: djangogoboot
Version: 1.0.2
Summary: Get a full Django stack up and running ASAP
Home-page: https://github.com/Apreche/djangogoboot/
License: MIT
Author: Scott Rubin
Author-email: apreche@frontrowcrew.com
Requires-Python: >=3.8,<4.0
Classifier: License :: OSI Approved :: MIT License
Classifier: Programming Language :: Python :: 3
Classifier: Programming Language :: Python :: 3.8
Classifier: Programming Language :: Python :: 3.9
Requires-Dist: Django (>=3.2,<4.0)
Requires-Dist: GitPython (>=3.1.14,<4.0.0)
Requires-Dist: Jinja2 (>=3.0.1,<4.0.0)
Requires-Dist: PyGithub (>=1.55,<2.0)
Requires-Dist: ansible (>=4.3.0,<5.0.0)
Requires-Dist: cryptography (>=3.4.7,<4.0.0)
Requires-Dist: paramiko (>=2.7.2,<3.0.0)
Requires-Dist: prompt-toolkit (>=3.0.18,<4.0.0)
Requires-Dist: requests (>=2.25.1,<3.0.0)
Project-URL: Repository, https://github.com/Apreche/djangogoboot/
